setup.py
pynoaa/__init__.py
pynoaa/pynoaa.py
pynoaa.egg-info/PKG-INFO
pynoaa.egg-info/SOURCES.txt
pynoaa.egg-info/dependency_links.txt
pynoaa.egg-info/not-zip-safe
pynoaa.egg-info/top_level.txt